proxlib/__about__.py
proxlib/operators.c
proxlib/operators.cpython-39-i386-linux-gnu.so
proxlib/__init__.py
proxlib-0.0.1.dist-info/LICENSE
proxlib-0.0.1.dist-info/METADATA
proxlib-0.0.1.dist-info/top_level.txt
proxlib-0.0.1.dist-info/WHEEL
proxlib-0.0.1.dist-info/RECORD
