Metadata-Version: 2.1
Name: proxlib
Version: 0.0.1
Summary: Prox-operator library for optimization
Home-page: https://github.com/UW-AMO/proxlib
Author: Peng Zheng
Author-email: zhengp@uw.eud
License: BSD 2-Clause License
Platform: UNKNOWN
Requires-Dist: numpy
Requires-Dist: scipy
Requires-Dist: cython
Provides-Extra: dev
Requires-Dist: pytest ; extra == 'dev'
Provides-Extra: docs
Provides-Extra: test
Requires-Dist: pytest ; extra == 'test'
